mctextrender/__init__.py
mctextrender/background.py
mctextrender/colors.py
mctextrender/image.py
mctextrender/text.py
mctextrender/tools.py
mctextrender/font/main.ttf
mctextrender-10.0.0.dist-info/licenses/LICENSE
mctextrender-10.0.0.dist-info/METADATA
mctextrender-10.0.0.dist-info/WHEEL
mctextrender-10.0.0.dist-info/top_level.txt
mctextrender-10.0.0.dist-info/RECORD
