Metadata-Version: 2.4
Name: mctextrender
Version: 10.0.0
Summary: A rendering library for Minecraft-style text and images
Author-email: Ventros <ventros.development@gmail.com>
License: MIT
License-File: LICENSE
Requires-Dist: Pillow
Dynamic: license-file
